timevec/__init__.py
timevec/_version.py
timevec/builtin_math.py
timevec/numpy.py
timevec/numpy_datetime64.py
timevec/py.typed
timevec/util.py
timevec-0.3.1.dist-info/LICENSE
timevec-0.3.1.dist-info/METADATA
timevec-0.3.1.dist-info/WHEEL
timevec-0.3.1.dist-info/top_level.txt
timevec-0.3.1.dist-info/RECORD
