Metadata-Version: 2.2
Name: timevec
Version: 0.3.1
Summary: Get some usable vector representations of datetime.
Author-email: Yui KITSU <kitsuyui+github@kitsuyui.com>
License: Copyright 2023-2025 Kitsu Yui
Project-URL: Homepage, https://github.com/kitsuyui/python-timevec
Classifier: Development Status :: 3 - Alpha
Classifier: License :: OSI Approved :: BSD License
Classifier: Programming Language :: Python :: 3.9
Classifier: Programming Language :: Python :: 3.10
Classifier: Programming Language :: Python :: 3.11
Classifier: Programming Language :: Python :: 3.12
Classifier: Programming Language :: Python :: 3.13
Classifier: Intended Audience :: Developers
Classifier: Topic :: Software Development :: Libraries
Requires-Python: >=3.9
License-File: LICENSE
Provides-Extra: numpy
Requires-Dist: numpy>=1.25.0; extra == "numpy"
